travis_ci_pypi_deploy_test.py
zabana_travis_ci_test-0.1.1.dist-info/LICENSE
zabana_travis_ci_test-0.1.1.dist-info/METADATA
zabana_travis_ci_test-0.1.1.dist-info/WHEEL
zabana_travis_ci_test-0.1.1.dist-info/top_level.txt
zabana_travis_ci_test-0.1.1.dist-info/RECORD
