Metadata-Version: 2.1
Name: zabana-travis-ci-test
Version: 0.1.1
Summary: A Python package to test the Travis-CI PyPI deploy.
Home-page: https://github.com/zabanaa/travis-ci-pypi-deploy-test
Author: Karim C
Author-email: jannis@leidel.info
License: MIT license
Platform: UNKNOWN
